archmap.py
archmap-0.5.dist-info/DESCRIPTION.rst
archmap-0.5.dist-info/METADATA
archmap-0.5.dist-info/RECORD
archmap-0.5.dist-info/WHEEL
archmap-0.5.dist-info/entry_points.txt
archmap-0.5.dist-info/metadata.json
archmap-0.5.dist-info/top_level.txt
