Metadata-Version: 2.0
Name: archmap
Version: 0.5
Summary: ArchMap GeoJSON/KML generator
Home-page: https://github.com/guyfawcus/ArchMap
Author: UNKNOWN
Author-email: UNKNOWN
License: Unlicense
Platform: UNKNOWN
Requires-Python: >=3
Requires-Dist: bs4
Requires-Dist: geojson
Requires-Dist: simplekml
